dockerfile_parse/__init__.py
dockerfile_parse/constants.py
dockerfile_parse/parser.py
dockerfile_parse/util.py
dockerfile_parse-1.0.0.dist-info/LICENSE
dockerfile_parse-1.0.0.dist-info/METADATA
dockerfile_parse-1.0.0.dist-info/WHEEL
dockerfile_parse-1.0.0.dist-info/top_level.txt
dockerfile_parse-1.0.0.dist-info/RECORD
